empower_functions/__init__.py
empower_functions/chat_handler.py
empower_functions/prompt.py
empower_functions/server.py
empower_functions-0.1.5.dist-info/METADATA
empower_functions-0.1.5.dist-info/WHEEL
empower_functions-0.1.5.dist-info/top_level.txt
empower_functions-0.1.5.dist-info/RECORD
