Metadata-Version: 2.1
Name: empower_functions
Version: 0.1.5
Summary: The empower_functions package provides a set of utility functions to run the empower-functions model
Author-email: "empower.dev" <yulong@empower.dev>
Project-URL: Homepage, https://empower.dev
Classifier: Programming Language :: Python :: 3
Classifier: License :: OSI Approved :: Apache Software License
Classifier: Operating System :: OS Independent
Requires-Python: >=3.8
Requires-Dist: jinja2
Requires-Dist: llama-cpp-python[server]
Requires-Dist: pydantic
